[
  {
    "id_issue": "1",
    "team": "team004",
    "device": "device003",
    "type": "type_issue003",
    "product": "A",
    "color": "44",
    "colornew": "",
    "transition_product": false,
    "productnew": "",
    "description_issue": "issue_procedure004",
    "time_create": "2024/10/26 14:37:57",
    "time_done": "2024/10/28",
    "hdkp": "hdkp_procedure003",
    "problem_solver": "problem_solver009",
    "person_log_issue": "person_log_issue015",
    "transition_color": false,
    "hdkp_other": ""
  },
  {
    "id_issue": "2",
    "team": "team002",
    "device": "device002",
    "type": "type_issue002",
    "product": "ss",
    "color": "saa",
    "colornew": "",
    "transition_product": false,
    "productnew": "",
    "description_issue": "issue_person008",
    "time_create": "2024/10/26 14:47:02",
    "time_done": "2024/10/28",
    "hdkp": "hdkp_person002",
    "problem_solver": "problem_solver011",
    "person_log_issue": "person_log_issue013",
    "transition_color": false,
    "hdkp_other": ""
  },
  {
    "id_issue": "3",
    "team": "team004",
    "device": "device003",
    "type": "type_issue003",
    "product": "ss",
    "color": "sssd",
    "colornew": "dds",
    "transition_product": false,
    "productnew": "",
    "description_issue": "issue_procedure004",
    "time_create": "2024/10/26 14:47:33",
    "time_done": "2024/10/28",
    "hdkp": "hdkp_procedure003",
    "problem_solver": "problem_solver004",
    "person_log_issue": "person_log_issue013",
    "transition_color": true,
    "hdkp_other": ""
  },
  {
    "id_issue": "4",
    "team": "team003",
    "device": "device002",
    "type": "type_issue002",
    "product": "&lt;script&gt;alert(&#39;&#39;);&lt;&#47;script&gt;",
    "color": "44",
    "colornew": "",
    "transition_product": false,
    "productnew": "",
    "description_issue": "issue_person001",
    "time_create": "2024/10/26 14:48:20",
    "time_done": "2024/10/26",
    "hdkp": "hdkp_person011",
    "problem_solver": "problem_solver003",
    "person_log_issue": "person_log_issue017",
    "transition_color": false
  },
  {
    "id_issue": "5",
    "team": "team001",
    "device": "device002",
    "type": "type_issue001",
    "product": "BC733",
    "color": "00A",
    "colornew": "",
    "transition_product": false,
    "productnew": "",
    "description_issue": "issue_device014",
    "time_create": "2024/10/26 15:31:20",
    "time_done": "2024/10/28",
    "hdkp": "hdkp_device004",
    "problem_solver": "problem_solver012",
    "person_log_issue": "person_log_issue016",
    "transition_color": false,
    "hdkp_other": ""
  },
  {
    "id_issue": "6",
    "team": "team002",
    "device": "device002",
    "type": "type_issue002",
    "product": "A",
    "color": "44",
    "colornew": "",
    "issue_other": "ffff",
    "hdkh_other": "",
    "transition_product": false,
    "productnew": "",
    "description_issue": "issue_person010",
    "time_create": "2024/10/26 20:58:34",
    "time_done": "2024/10/31",
    "hdkp": "hdkp_person011",
    "problem_solver": "problem_solver001",
    "person_log_issue": "person_log_issue017",
    "transition_color": false,
    "hdkp_other": "demo"
  },
  {
    "id_issue": "7",
    "team": "team002",
    "device": "device002",
    "type": "type_issue002",
    "product": "A",
    "color": "44",
    "colornew": "",
    "issue_other": "aaa",
    "hdkh_other": "",
    "transition_product": false,
    "productnew": "",
    "description_issue": "issue_person010",
    "time_create": "2024/10/26 21:28:57",
    "time_done": "2024/10/28",
    "hdkp": "hdkp_person008",
    "problem_solver": "problem_solver007",
    "person_log_issue": "person_log_issue013",
    "transition_color": false,
    "hdkp_other": ""
  },
  {
    "id_issue": "8",
    "team": "team001",
    "device": "device002",
    "type": "type_issue002",
    "product": "1111",
    "color": "00A",
    "colornew": "222111",
    "issue_other": "",
    "hdkh_other": "",
    "transition_product": false,
    "productnew": "",
    "description_issue": "issue_person007",
    "time_create": "2024/10/26 22:17:41",
    "time_done": "2024/10/28",
    "hdkp": "hdkp_person011",
    "problem_solver": "problem_solver016",
    "person_log_issue": "person_log_issue012",
    "transition_color": true,
    "hdkp_other": "ss"
  },
  {
    "id_issue": "9",
    "team": "team001",
    "device": "device002",
    "type": "type_issue002",
    "product": "1111",
    "color": "00A",
    "colornew": "222111",
    "issue_other": "",
    "hdkh_other": "",
    "transition_product": false,
    "productnew": "",
    "description_issue": "issue_person008",
    "time_create": "2024/10/26 22:34:35",
    "time_done": "2024/10/28",
    "hdkp": "hdkp_person002",
    "problem_solver": "problem_solver008",
    "person_log_issue": "person_log_issue012",
    "transition_color": true,
    "hdkp_other": ""
  },
  {
    "id_issue": "10",
    "team": "team001",
    "device": "device002",
    "type": "type_issue003",
    "product": "1111",
    "color": "00A",
    "colornew": "222111",
    "issue_other": "",
    "hdkh_other": "",
    "transition_product": false,
    "productnew": "",
    "description_issue": "issue_procedure003",
    "time_create": "2024/10/26 22:35:09",
    "time_done": "2024/10/30",
    "hdkp": "hdkp_procedure006",
    "problem_solver": "problem_solver017",
    "person_log_issue": "person_log_issue012",
    "transition_color": true,
    "hdkp_other": "Demo new 14444"
  },
  {
    "id_issue": "11",
    "team": "team002",
    "device": "device003",
    "type": "type_issue001",
    "product": "bc733",
    "color": "00A",
    "colornew": "",
    "issue_other": "sssss11111",
    "hdkh_other": "",
    "transition_product": true,
    "productnew": "aq108",
    "description_issue": "issue_device014",
    "time_create": "2024/10/28 08:23:03",
    "time_done": "2024/10/28",
    "hdkp": "hdkp_device002",
    "problem_solver": "problem_solver016",
    "person_log_issue": "person_log_issue013",
    "transition_color": false,
    "hdkp_other": ""
  },
  {
    "id_issue": "12",
    "team": "team001",
    "device": "device002",
    "type": "type_issue001",
    "product": "ss",
    "color": "21111",
    "colornew": "",
    "issue_other": "111222111",
    "hdkh_other": "",
    "transition_product": false,
    "productnew": "",
    "description_issue": "issue_device014",
    "time_create": "2024/10/28 08:34:32",
    "time_done": "2024/10/28",
    "hdkp": "hdkp_device007",
    "problem_solver": "problem_solver016",
    "person_log_issue": "person_log_issue015",
    "transition_color": false,
    "hdkp_other": "22222222"
  },
  {
    "id_issue": "13",
    "team": "team006",
    "device": "device006",
    "type": "type_issue001",
    "product": "0",
    "color": "11",
    "colornew": "",
    "issue_other": "",
    "hdkh_other": "",
    "transition_product": true,
    "productnew": "1",
    "description_issue": "issue_device013",
    "time_create": "2024/10/28 09:39:10",
    "time_done": "2024/10/28",
    "hdkp": "hdkp_device001",
    "problem_solver": "problem_solver014",
    "person_log_issue": "person_log_issue007",
    "transition_color": false,
    "hdkp_other": ""
  },
  {
    "id_issue": "14",
    "team": "team006",
    "device": "device001",
    "type": "type_issue002",
    "product": "bc123",
    "color": "5",
    "colornew": "6",
    "issue_other": "",
    "hdkh_other": "",
    "transition_product": false,
    "productnew": "",
    "description_issue": "issue_person009",
    "time_create": "2024/10/28 09:50:18",
    "time_done": "2024/10/28",
    "hdkp": "hdkp_person009",
    "problem_solver": "problem_solver012",
    "person_log_issue": "person_log_issue004",
    "transition_color": true,
    "hdkp_other": ""
  },
  {
    "id_issue": "15",
    "team": "team001",
    "device": "device001",
    "type": "type_issue002",
    "product": "1",
    "color": "aa",
    "colornew": "bb",
    "issue_other": "",
    "hdkh_other": "",
    "transition_product": false,
    "productnew": "",
    "description_issue": "issue_person003",
    "time_create": "2024/10/28 09:52:43",
    "time_done": "2024/10/29",
    "hdkp": "hdkp_person009",
    "problem_solver": "problem_solver010",
    "person_log_issue": "person_log_issue010",
    "transition_color": true,
    "hdkp_other": ""
  },
  {
    "id_issue": "16",
    "team": "team001",
    "device": "device001",
    "type": "type_issue001",
    "product": "1111",
    "color": "00A",
    "colornew": "ssss",
    "issue_other": "",
    "hdkh_other": "",
    "transition_product": false,
    "productnew": "",
    "description_issue": "issue_device012",
    "time_create": "2024/10/28 09:58:34",
    "time_done": "2024/10/29",
    "hdkp": "hdkp_device003",
    "problem_solver": "problem_solver010",
    "person_log_issue": "person_log_issue013",
    "transition_color": true,
    "hdkp_other": ""
  },
  {
    "id_issue": "17",
    "team": "team002",
    "device": "device001",
    "type": "type_issue001",
    "product": "bc733",
    "color": "010",
    "colornew": "",
    "issue_other": "",
    "hdkh_other": "",
    "transition_product": false,
    "productnew": "",
    "description_issue": "issue_device004",
    "time_create": "2024/11/04 15:00:57",
    "time_done": "2024/11/04",
    "hdkp": "hdkp_device001",
    "problem_solver": "problem_solver014",
    "person_log_issue": "person_log_issue010",
    "transition_color": false,
    "hdkp_other": ""
  }
]